infoga.py
infoga_ng-0.0.1.dist-info/licenses/LICENSE
infoga_ng-0.0.1.dist-info/METADATA
infoga_ng-0.0.1.dist-info/WHEEL
infoga_ng-0.0.1.dist-info/entry_points.txt
infoga_ng-0.0.1.dist-info/top_level.txt
infoga_ng-0.0.1.dist-info/RECORD
