Metadata-Version: 2.4
Name: infoga-ng
Version: 0.0.1
Summary: Email OSINT tool to gather information from public sources
Author-email: Mertcan GÖKGÖZ <mertcan@gokgoz.net>
License-Expression: GPL-3.0-or-later
Project-URL: Homepage, https://github.com/mertcangokgoz/infoga
Classifier: Programming Language :: Python :: 3
Classifier: Operating System :: OS Independent
Requires-Python: >=3.10
License-File: LICENSE
Requires-Dist: colorama==0.4.6
Requires-Dist: requests==2.32.3
Requires-Dist: urllib3==2.4.0
Dynamic: license-file
